ebb_lint/__init__.py
ebb_lint/_version.py
ebb_lint/errors.py
ebb_lint/flake8.py
ebb_lint/checkers/__init__.py
ebb_lint/checkers/check_docstrings.py
ebb_lint/checkers/check_misc_dubious_syntax.py
ebb_lint/checkers/check_trailing_commas.py
ebb_lint/checkers/registration.py
ebb_lint/test/__init__.py
ebb_lint/test/test_flake8.py
ebb_lint-0.19.1.0.dist-info/LICENSE
ebb_lint-0.19.1.0.dist-info/METADATA
ebb_lint-0.19.1.0.dist-info/WHEEL
ebb_lint-0.19.1.0.dist-info/entry_points.txt
ebb_lint-0.19.1.0.dist-info/top_level.txt
ebb_lint-0.19.1.0.dist-info/RECORD
