Metadata-Version: 2.1
Name: ebb-lint
Version: 0.19.1.0
Summary: lint for ensuring quality software
Home-page: https://github.com/pyga/ebb-lint
Author: Python Grammar Authority
Author-email: mrw@enotuniq.org
License: MIT
Platform: UNKNOWN
Classifier: Development Status :: 3 - Alpha
Classifier: Environment :: Plugins
Classifier: Intended Audience :: Developers
Classifier: License :: OSI Approved :: MIT License
Classifier: Operating System :: OS Independent
Classifier: Programming Language :: Python :: 2.7
Classifier: Programming Language :: Python :: 3.3
Classifier: Programming Language :: Python :: 3.4
Classifier: Programming Language :: Python :: 3.5
Classifier: Topic :: Software Development :: Quality Assurance
Requires-Dist: awpa (>=0.16.1.0)
Requires-Dist: flake8-polyfill
Requires-Dist: flake8 (>=2.6.0)
Requires-Dist: intervaltree (>=3.0.0)
Requires-Dist: six
Requires-Dist: venusian
Requires-Dist: enum34 ; python_version < "3.4"
Provides-Extra: all
Requires-Dist: coverage ; extra == 'all'
Requires-Dist: pytest (>=4<5) ; extra == 'all'
Requires-Dist: pytest-cov ; extra == 'all'
Requires-Dist: enum34 ; extra == 'all'
Provides-Extra: dev
Requires-Dist: coverage ; extra == 'dev'
Requires-Dist: pytest (>=4<5) ; extra == 'dev'
Requires-Dist: pytest-cov ; extra == 'dev'
